CHANGES
MANIFEST.in
README.md
README.rst
requirements.txt
setup.py
zcheck/__init__.py
zcheck/bucket.py
zcheck/check.py
zcheck/cli.py
zcheck/error.py
zcheck/format.py
zcheck/forward.py
zcheck/helm.py
zcheck/log.py
zcheck/orbit.py
zcheck/print.py
zcheck/s3.py
zcheck/util.py
zcheck.egg-info/PKG-INFO
zcheck.egg-info/SOURCES.txt
zcheck.egg-info/dependency_links.txt
zcheck.egg-info/entry_points.txt
zcheck.egg-info/requires.txt
zcheck.egg-info/top_level.txt