Metadata-Version: 1.1
Name: zcheck
Version: 0.1.5
Summary: A utility to check the configuration of a running Zenko cluster targeted at sysadmins
Home-page: UNKNOWN
Author: Taylor McKinnon
Author-email: taylor.mckinnon@scality.com
License: UNKNOWN
Keywords: scality zenko orbit
Platform: UNKNOWN
Classifier: Development Status :: 3 - Alpha
Classifier: Intended Audience :: Developers
Classifier: License :: OSI Approved :: Apache Software License
Classifier: Programming Language :: Python :: 3
Classifier: Programming Language :: Python :: 3.6
